emailmgr
