Metadata-Version: 1.0
Name: django-emailmgr
Version: 0.9
Summary: An email manager for Django user
Home-page: https://github.com/un33k/django-emailmgr
Author: Val L33
Author-email: val@neekware.com
License: UNKNOWN
Platform: UNKNOWN
Classifier: Development Status :: 4 - Beta
Classifier: Environment :: Web Environment
Classifier: Intended Audience :: Developers
Classifier: License :: OSI Approved :: BSD License
Classifier: Operating System :: OS Independent
Classifier: Programming Language :: Python
Classifier: Topic :: Utilities
